ObjectAsString/ObjectAsString.py
ObjectAsString/ObjectAsString_tests.py
ObjectAsString/ObjectAsString_versus_string.py
ObjectAsString-1.dist-info/LICENSE
ObjectAsString-1.dist-info/METADATA
ObjectAsString-1.dist-info/WHEEL
ObjectAsString-1.dist-info/entry_points.txt
ObjectAsString-1.dist-info/top_level.txt
ObjectAsString-1.dist-info/RECORD
