Metadata-Version: 2.1
Name: ObjectAsString
Version: 1
Summary: This package contains implementation of the library "ObjectAsString". ObjectAsString is a library which makes coding in Python feel like Java and JavaScript. "+" operator will automatically be string concatenation if non-numeric types are involved.
Home-page: https://github.com/DigitalCreativeApkDev/ObjectAsString
Author: DigitalCreativeApkDev
Author-email: digitalcreativeapkdev2022@gmail.com
License: MIT
Platform: UNKNOWN
Classifier: Programming Language :: Python :: 3
Classifier: Programming Language :: Python :: 3.7
